footil/__init__.py
footil/date.py
footil/datetime.py
footil/decor.py
footil/file.py
footil/formatting.py
footil/log.py
footil/parsing.py
footil/path.py
footil/patterns.py
footil/sorting.py
footil/time.py
footil/version.py
footil/xcollections.py
footil/xdata.py
footil/xiter.py
footil/xtyping.py
footil/tools/__init__.py
footil/tools/string_pattern_methods.py
footil-0.35.0.dist-info/LICENSE
footil-0.35.0.dist-info/METADATA
footil-0.35.0.dist-info/WHEEL
footil-0.35.0.dist-info/top_level.txt
footil-0.35.0.dist-info/RECORD
