Metadata-Version: 2.1
Name: footil
Version: 0.35.0
Summary: Various Python helpers for other projects
Home-page: https://github.com/focusate/footil
Maintainer: Andrius Laukavičius
Maintainer-email: dev@focusate.eu
License: LGPLv3
Platform: UNKNOWN
Classifier: Environment :: Other Environment
Classifier: Intended Audience :: Developers
Classifier: Programming Language :: Python :: 3.5
Classifier: Programming Language :: Python :: 3.6
Classifier: Programming Language :: Python :: 3.7
Classifier: Programming Language :: Python :: 3.8
Classifier: Topic :: Software Development
Classifier: Topic :: Utilities
Requires-Python: >=3.5
License-File: LICENSE
Requires-Dist: yattag
Requires-Dist: python-dateutil
Requires-Dist: verboselogs
Requires-Dist: semver (<=2.13.0)
Requires-Dist: natsort
Provides-Extra: test
Requires-Dist: pytest ; extra == 'test'
Requires-Dist: mock ; extra == 'test'
